eml_to_pdf/__init__.py
eml_to_pdf/cli.py
eml_to_pdf/converter.py
eml_to_pdf/merger.py
eml_to_pdf-1.0.0.dist-info/licenses/LICENSE
eml_to_pdf-1.0.0.dist-info/METADATA
eml_to_pdf-1.0.0.dist-info/WHEEL
eml_to_pdf-1.0.0.dist-info/entry_points.txt
eml_to_pdf-1.0.0.dist-info/top_level.txt
eml_to_pdf-1.0.0.dist-info/RECORD
