Metadata-Version: 2.4
Name: eml-to-pdf
Version: 1.0.0
Summary: A professional Python package for converting EML email files to PDF format
Home-page: https://github.com/AlienZaki/eml-to-pdf
Author: Abdullah Zaki
Author-email: Abdullah Zaki <zakiapdu10@gmail.com>
Maintainer-email: Abdullah Zaki <zakiapdu10@gmail.com>
License: MIT
Project-URL: Homepage, https://github.com/AlienZaki/eml-to-pdf
Project-URL: Documentation, https://github.com/AlienZaki/eml-to-pdf#readme
Project-URL: Repository, https://github.com/AlienZaki/eml-to-pdf.git
Project-URL: Bug Tracker, https://github.com/AlienZaki/eml-to-pdf/issues
Keywords: eml,email,pdf,conversion,html,weasyprint
Classifier: Development Status :: 5 - Production/Stable
Classifier: Intended Audience :: Developers
Classifier: Intended Audience :: End Users/Desktop
Classifier: Operating System :: OS Independent
Classifier: Programming Language :: Python :: 3
Classifier: Programming Language :: Python :: 3.8
Classifier: Programming Language :: Python :: 3.9
Classifier: Programming Language :: Python :: 3.10
Classifier: Programming Language :: Python :: 3.11
Classifier: Programming Language :: Python :: 3.12
Classifier: Topic :: Communications :: Email
Classifier: Topic :: Office/Business
Classifier: Topic :: Text Processing :: Markup :: HTML
Classifier: Topic :: Utilities
Requires-Python: >=3.8
License-File: LICENSE
Requires-Dist: weasyprint>=60.0
Requires-Dist: PyPDF2>=3.0.0
Requires-Dist: Pillow>=9.0.0
Requires-Dist: build>=1.2.2.post1
Requires-Dist: twine>=6.1.0
Provides-Extra: dev
Requires-Dist: pytest>=6.0; extra == "dev"
Requires-Dist: pytest-cov>=2.0; extra == "dev"
Requires-Dist: black>=22.0; extra == "dev"
Requires-Dist: flake8>=4.0; extra == "dev"
Requires-Dist: mypy>=0.900; extra == "dev"
Requires-Dist: pre-commit>=2.0; extra == "dev"
Dynamic: author
Dynamic: home-page
Dynamic: license-file
Dynamic: requires-python
